dcor_shared/__init__.py
dcor_shared/_version.py
dcor_shared/ckan.py
dcor_shared/data.py
dcor_shared/dcinst.py
dcor_shared/mime.py
dcor_shared/parse.py
dcor_shared/paths.py
dcor_shared/rqjob.py
dcor_shared/s3.py
dcor_shared/s3cc.py
dcor_shared/testing.py
dcor_shared/util.py
dcor_shared-1.0.4.dist-info/licenses/LICENSE
dcor_shared-1.0.4.dist-info/METADATA
dcor_shared-1.0.4.dist-info/WHEEL
dcor_shared-1.0.4.dist-info/top_level.txt
dcor_shared-1.0.4.dist-info/RECORD
