Metadata-Version: 2.4
Name: dcor_shared
Version: 1.0.4
Summary: Functionalities shared by the DCOR CKAN extensions
Author: Paul Müller
Maintainer-email: Paul Müller <dev@craban.de>
License: GNU Affero General Public License v3 or later (AGPLv3+)
Project-URL: source, https://github.com/DCOR-dev/dcor_shared
Project-URL: tracker, https://github.com/DCOR-dev/dcor_shared/issues
Project-URL: changelog, https://github.com/DCOR-dev/dcor_shared/blob/main/CHANGELOG
Keywords: DC,DCOR,deformability,cytometry
Classifier: Operating System :: OS Independent
Classifier: Programming Language :: Python :: 3
Classifier: Topic :: Scientific/Engineering :: Visualization
Classifier: Intended Audience :: Science/Research
Requires-Python: <4,>=3.8
License-File: LICENSE
Requires-Dist: boto3
Requires-Dist: dclab[s3]>=0.64.0
Dynamic: license-file
